LICENSE
README.md
setup.cfg
setup.py
siranga/__init__.py
siranga/__main__.py
siranga/config.py
siranga/helpers.py
siranga/nested.py
siranga/prompt.py
siranga/validators.py
siranga.egg-info/PKG-INFO
siranga.egg-info/SOURCES.txt
siranga.egg-info/dependency_links.txt
siranga.egg-info/entry_points.txt
siranga.egg-info/requires.txt
siranga.egg-info/top_level.txt