Metadata-Version: 2.1
Name: siranga
Version: 0.3.7
Summary: SSH Utility
Home-page: UNKNOWN
Author: Wh1t3Fox
Author-email: dev@exploit.design
License: MIT
Keywords: ssh
Platform: UNKNOWN
Classifier: Development Status :: 3 - Alpha
Classifier: Intended Audience :: End Users/Desktop
Classifier: License :: OSI Approved :: MIT License
Classifier: Programming Language :: Python :: 3
Classifier: Operating System :: POSIX :: Linux
Classifier: Environment :: Console
Provides-Extra: dev
License-File: LICENSE
